z3c/pagelet/README.rst
z3c/pagelet/__init__.py
z3c/pagelet/browser.py
z3c/pagelet/configure.zcml
z3c/pagelet/form.pt
z3c/pagelet/form.zcml
z3c/pagelet/index.rst
z3c/pagelet/interfaces.py
z3c/pagelet/meta.zcml
z3c/pagelet/outputchecker.py
z3c/pagelet/provider.py
z3c/pagelet/tests.py
z3c/pagelet/zcml.py
z3c/pagelet/zcml.rst
z3c_pagelet-4.0.dist-info/LICENSE.rst
z3c_pagelet-4.0.dist-info/METADATA
z3c_pagelet-4.0.dist-info/WHEEL
z3c_pagelet-4.0.dist-info/top_level.txt
z3c_pagelet-4.0.dist-info/RECORD
