Metadata-Version: 2.2
Name: z3c.pagelet
Version: 4.0
Summary: Pagelets are way to specify a template without the O-wrap.
Home-page: https://github.com/zopefoundation/z3c.pagelet
Author: Roger Ineichen and the Zope Community
Author-email: zope-dev@zope.dev
License: ZPL-2.1
Keywords: zope3 template pagelet layout zpt pagetemplate
Classifier: Development Status :: 5 - Production/Stable
Classifier: Environment :: Web Environment
Classifier: Intended Audience :: Developers
Classifier: License :: OSI Approved :: Zope Public License
Classifier: Programming Language :: Python
Classifier: Programming Language :: Python :: 3
Classifier: Programming Language :: Python :: 3.9
Classifier: Programming Language :: Python :: 3.10
Classifier: Programming Language :: Python :: 3.11
Classifier: Programming Language :: Python :: 3.12
Classifier: Programming Language :: Python :: 3.13
Classifier: Programming Language :: Python :: Implementation :: CPython
Classifier: Natural Language :: English
Classifier: Operating System :: OS Independent
Classifier: Topic :: Internet :: WWW/HTTP
Classifier: Framework :: Zope :: 3
Requires-Python: >=3.9
License-File: LICENSE.rst
Requires-Dist: setuptools
Requires-Dist: z3c.template>=1.2.0
Requires-Dist: zope.browserpage
Requires-Dist: zope.component>=3.7.0
Requires-Dist: zope.configuration
Requires-Dist: zope.contentprovider
Requires-Dist: zope.interface
Requires-Dist: zope.publisher
Requires-Dist: zope.schema
Requires-Dist: zope.security
Provides-Extra: test
Requires-Dist: zope.formlib; extra == "test"
Requires-Dist: zope.site; extra == "test"
Requires-Dist: zope.testing; extra == "test"
Requires-Dist: zope.testrunner>=6.4; extra == "test"
Requires-Dist: zope.traversing; extra == "test"
Requires-Dist: lxml; extra == "test"
Requires-Dist: z3c.pt>=2.1; extra == "test"
Requires-Dist: z3c.ptcompat>=1.0; extra == "test"
Provides-Extra: chameleon
Requires-Dist: z3c.pt>=2.1; extra == "chameleon"
Requires-Dist: z3c.ptcompat; extra == "chameleon"
Provides-Extra: forms
Requires-Dist: zope.formlib; extra == "forms"
Provides-Extra: docs
Requires-Dist: z3c.recipe.sphinxdoc; extra == "docs"
Dynamic: author
Dynamic: author-email
Dynamic: classifier
Dynamic: description
Dynamic: home-page
Dynamic: keywords
Dynamic: license
Dynamic: provides-extra
Dynamic: requires-dist
Dynamic: requires-python
Dynamic: summary
